{
  "$schema": "https://json-schema.org/draft/2020-12/schema",
  "title": "Story Packet",
  "type": "object",
  "required": [
    "id",
    "title",
    "status",
    "lane",
    "product_contract",
    "acceptance_criteria",
    "validation"
  ],
  "properties": {
    "id": { "type": "string", "pattern": "^US-[0-9]{3}$" },
    "title": { "type": "string" },
    "status": { "enum": ["planned", "ready", "in_progress", "review", "done", "blocked"] },
    "lane": { "enum": ["tiny", "normal", "high-risk"] },
    "product_contract": { "type": "string" },
    "acceptance_criteria": { "type": "array", "items": { "type": "string" } },
    "validation": { "type": "object" }
  }
}
